langgraph_serving_example/app/async_client.py
langgraph_serving_example/app/client.py
langgraph_serving_example/app/server.py
langgraph_serving_example/app/type.py
langgraph_serving_example/flows/__init__.py
langgraph_serving_example/flows/asset/graph.png
langgraph_serving_example/flows/base.py
langgraph_serving_example/flows/graph.py
langgraph_serving_example/flows/nodes.py
langgraph_serving_example/flows/utils.py
langgraph_serving_example-0.1.0.dist-info/METADATA
langgraph_serving_example-0.1.0.dist-info/WHEEL
langgraph_serving_example-0.1.0.dist-info/RECORD
