Metadata-Version: 2.1
Name: langgraph_serving_example
Version: 0.1.0
Summary: Example of LangGraph and Serving
License: Proprietary
Author: dayoungMM
Author-email: dalgeetm@gmail.com
Classifier: License :: Other/Proprietary License
Classifier: Programming Language :: Python :: 2
Classifier: Programming Language :: Python :: 2.7
Classifier: Programming Language :: Python :: 3
Classifier: Programming Language :: Python :: 3.4
Classifier: Programming Language :: Python :: 3.5
Classifier: Programming Language :: Python :: 3.6
Classifier: Programming Language :: Python :: 3.7
Classifier: Programming Language :: Python :: 3.8
Classifier: Programming Language :: Python :: 3.9
Classifier: Programming Language :: Python :: 3.10
Classifier: Programming Language :: Python :: 3.11
Classifier: Programming Language :: Python :: 3.12
Requires-Dist: fastapi (>=0.115.0,<0.116.0)
Requires-Dist: langchain (>=0.3.0,<0.4.0)
Requires-Dist: langchain-community (>=0.3.0,<0.4.0)
Requires-Dist: langchain-core (>=0.3.2,<0.4.0)
Requires-Dist: langchain-experimental (>=0.3.0,<0.4.0)
Requires-Dist: langchain-openai (>=0.2.0,<0.3.0)
Requires-Dist: langgraph (>=0.2.26,<0.3.0)
Requires-Dist: langserve[all] (>=0.3.0,<0.4.0)
Requires-Dist: nest_asyncio (>=1.6.0,<2.0.0)
Requires-Dist: pyppeteer (>=2.0.0,<3.0.0)
Requires-Dist: sse_starlette (>=1.8.2,<2.0.0)
Requires-Dist: wikipedia (>=1.4.0,<2.0.0)
